{
    "client": {
        "type": "connect",
        "participantId": "A0D00061575B499A8080DBF3CACA6A08",
        "assignmentId": "cdec26e6-b419-4196-8932-f923cc810dba",
        "projectId": "d286e2d1-0ca9-4f2b-a8d9-4b260efb0482",
        "sid": "connect-A0D00061575B499A8080DBF3CACA6A08",
        "url": "https:\/\/lo.velezlab.opalstacked.com\/crayon-coaster\/index.html?participantId=A0D00061575B499A8080DBF3CACA6A08&assignmentId=cdec26e6-b419-4196-8932-f923cc810dba&projectId=d286e2d1-0ca9-4f2b-a8d9-4b260efb0482",
        "window": {
            "width": 1008,
            "height": 608
        },
        "screen": {
            "width": 1024,
            "height": 768
        },
        "starttime": 1703708903716,
        "userAgent": "Mozilla\/5.0 (Windows NT 10.0; Win64; x64) AppleWebKit\/537.36 (KHTML, like Gecko) Chrome\/109.0.0.0 Safari\/537.36"
    },
    "version": "crayon_coaster_test",
    "stroke": [],
    "data": [
        {
            "exptPart": "tutorial",
            "numTrial": 0,
            "levelIndex": 0,
            "levelID": "short_drop",
            "marbleStartLoc": {
                "x": 0.1,
                "y": 0.075
            },
            "cupLoc": {
                "x": 0.1,
                "y": 0.5
            },
            "blockLoc": [],
            "gravX": 0,
            "gravY": 1,
            "mass": 1,
            "radius": 20,
            "numAttempts": 0,
            "maxAttempt": 5,
            "marbleEndLoc": {
                "x": 80,
                "y": 344.9452979386293
            },
            "marbleCoords": [
                {
                    "x": 80,
                    "y": 344.9452979386293
                },
                {
                    "x": 80,
                    "y": 344.9452979386293
                },
                {
                    "x": 80,
                    "y": 344.9452979386293
                },
                {
                    "x": 80,
                    "y": 344.9452979386293
                },
                {
                    "x": 80,
                    "y": 344.9452979386293
                },
                {
                    "x": 80,
                    "y": 344.9452979386293
                },
                {
                    "x": 80,
                    "y": 344.9452979386293
                },
                {
                    "x": 80,
                    "y": 344.9452979386293
                },
                {
                    "x": 80,
                    "y": 344.9452979386293
                },
                {
                    "x": 80,
                    "y": 344.9452979386293
                },
                {
                    "x": 80,
                    "y": 344.9452979386293
                },
                {
                    "x": 80,
                    "y": 344.9452979386293
                },
                {
                    "x": 80,
                    "y": 344.9452979386293
                },
                {
                    "x": 80,
                    "y": 344.9452979386293
                },
                {
                    "x": 80,
                    "y": 344.9452979386293
                },
                {
                    "x": 80,
                    "y": 344.9452979386293
                },
                {
                    "x": 80,
                    "y": 344.9452979386293
                },
                {
                    "x": 80,
                    "y": 344.9452979386293
                },
                {
                    "x": 80,
                    "y": 344.9452979386293
                },
                {
                    "x": 80,
                    "y": 344.9452979386293
                },
                {
                    "x": 80,
                    "y": 344.9452979386293
                },
                {
                    "x": 80,
                    "y": 344.9452979386293
                },
                {
                    "x": 80,
                    "y": 344.9452979386293
                },
                {
                    "x": 80,
                    "y": 344.9452979386293
                },
                {
                    "x": 80,
                    "y": 344.9452979386293
                },
                {
                    "x": 80,
                    "y": 344.9452979386293
                },
                {
                    "x": 80,
                    "y": 344.9452979386293
                },
                {
                    "x": 80,
                    "y": 344.9452979386293
                },
                {
                    "x": 80,
                    "y": 344.9452979386293
                },
                {
                    "x": 80,
                    "y": 344.9452979386293
                },
                {
                    "x": 80,
                    "y": 344.9452979386293
                },
                {
                    "x": 80,
                    "y": 344.9452979386293
                },
                {
                    "x": 80,
                    "y": 344.9452979386293
                },
                {
                    "x": 80,
                    "y": 344.9452979386293
                },
                {
                    "x": 80,
                    "y": 344.9452979386293
                },
                {
                    "x": 80,
                    "y": 344.9452979386293
                },
                {
                    "x": 80,
                    "y": 344.9452979386293
                },
                {
                    "x": 80,
                    "y": 344.9452979386293
                },
                {
                    "x": 80,
                    "y": 344.9452979386293
                },
                {
                    "x": 80,
                    "y": 344.9452979386293
                },
                {
                    "x": 80,
                    "y": 344.9452979386293
                },
                {
                    "x": 80,
                    "y": 344.9452979386293
                },
                {
                    "x": 80,
                    "y": 344.9452979386293
                },
                {
                    "x": 80,
                    "y": 344.9452979386293
                },
                {
                    "x": 80,
                    "y": 344.9452979386293
                },
                {
                    "x": 80,
                    "y": 344.9452979386293
                },
                {
                    "x": 80,
                    "y": 344.9452979386293
                },
                {
                    "x": 80,
                    "y": 344.9452979386293
                },
                {
                    "x": 80,
                    "y": 344.9452979386293
                },
                {
                    "x": 80,
                    "y": 344.9452979386293
                },
                {
                    "x": 80,
                    "y": 344.9452979386293
                },
                {
                    "x": 80,
                    "y": 344.9452979386293
                },
                {
                    "x": 80,
                    "y": 344.9452979386293
                },
                {
                    "x": 80,
                    "y": 344.9452979386293
                },
                {
                    "x": 80,
                    "y": 344.9452979386293
                },
                {
                    "x": 80,
                    "y": 344.9452979386293
                },
                {
                    "x": 80,
                    "y": 344.9452979386293
                },
                {
                    "x": 80,
                    "y": 344.9452979386293
                },
                {
                    "x": 80,
                    "y": 344.9452979386293
                },
                {
                    "x": 80,
                    "y": 344.9452979386293
                },
                {
                    "x": 80,
                    "y": 344.9452979386293
                },
                {
                    "x": 80,
                    "y": 344.9452979386293
                },
                {
                    "x": 80,
                    "y": 344.9452979386293
                },
                {
                    "x": 80,
                    "y": 344.9452979386293
                },
                {
                    "x": 80,
                    "y": 344.9452979386293
                },
                {
                    "x": 80,
                    "y": 344.9452979386293
                },
                {
                    "x": 80,
                    "y": 344.9452979386293
                },
                {
                    "x": 80,
                    "y": 344.9452979386293
                },
                {
                    "x": 80,
                    "y": 344.9452979386293
                },
                {
                    "x": 80,
                    "y": 344.9452979386293
                },
                {
                    "x": 80,
                    "y": 344.9452979386293
                },
                {
                    "x": 80,
                    "y": 344.9452979386293
                },
                {
                    "x": 80,
                    "y": 344.9452979386293
                },
                {
                    "x": 80,
                    "y": 344.9452979386293
                },
                {
                    "x": 80,
                    "y": 344.9452979386293
                },
                {
                    "x": 80,
                    "y": 344.9452979386293
                },
                {
                    "x": 80,
                    "y": 344.9452979386293
                },
                {
                    "x": 80,
                    "y": 344.9452979386293
                },
                {
                    "x": 80,
                    "y": 344.9452979386293
                },
                {
                    "x": 80,
                    "y": 344.9452979386293
                },
                {
                    "x": 80,
                    "y": 344.9452979386293
                }
            ],
            "marbleEndDist": 0,
            "marbleMinDist": 0,
            "runOutcome": "goal",
            "drawnLines": [],
            "drawnPhysObj": [],
            "trialStartTime": 1703708920615,
            "drawTime": 20098,
            "runTime": 5799
        }
    ],
    "tutorialsurvey": [],
    "endsurvey": null,
    "demographic": null,
    "bonus": ""
}