{
    "client": {
        "type": "connect",
        "participantId": "B19D08B7E13D4CBFB503C08C6E51FF96",
        "assignmentId": "1b2ca1d7-6e18-48d4-8fc1-3e767b5aa6ab",
        "projectId": "d286e2d1-0ca9-4f2b-a8d9-4b260efb0482",
        "sid": "connect-B19D08B7E13D4CBFB503C08C6E51FF96",
        "url": "https:\/\/lo.velezlab.opalstacked.com\/crayon-coaster\/index.html?participantId=B19D08B7E13D4CBFB503C08C6E51FF96&assignmentId=1b2ca1d7-6e18-48d4-8fc1-3e767b5aa6ab&projectId=d286e2d1-0ca9-4f2b-a8d9-4b260efb0482",
        "window": {
            "width": 1498,
            "height": 686
        },
        "screen": {
            "width": 1348,
            "height": 758
        },
        "starttime": 1703865010145,
        "userAgent": "Mozilla\/5.0 (Windows NT 10.0; Win64; x64) AppleWebKit\/537.36 (KHTML, like Gecko) Chrome\/120.0.0.0 Safari\/537.36"
    },
    "version": "crayon_coaster_test",
    "stroke": [],
    "data": [
        {
            "exptPart": "tutorial",
            "numTrial": 0,
            "levelIndex": 0,
            "levelID": "short_drop",
            "marbleStartLoc": {
                "x": 0.1,
                "y": 0.075
            },
            "cupLoc": {
                "x": 0.1,
                "y": 0.5
            },
            "blockLoc": [],
            "gravX": 0,
            "gravY": 1,
            "mass": 1,
            "radius": 20,
            "numAttempts": 0,
            "maxAttempt": 5,
            "marbleEndLoc": {
                "x": 80,
                "y": 345.13396321821295
            },
            "marbleCoords": [
                {
                    "x": 80,
                    "y": 345.13396321821295
                },
                {
                    "x": 80,
                    "y": 345.13396321821295
                },
                {
                    "x": 80,
                    "y": 345.13396321821295
                },
                {
                    "x": 80,
                    "y": 345.13396321821295
                },
                {
                    "x": 80,
                    "y": 345.13396321821295
                },
                {
                    "x": 80,
                    "y": 345.13396321821295
                },
                {
                    "x": 80,
                    "y": 345.13396321821295
                },
                {
                    "x": 80,
                    "y": 345.13396321821295
                },
                {
                    "x": 80,
                    "y": 345.13396321821295
                },
                {
                    "x": 80,
                    "y": 345.13396321821295
                },
                {
                    "x": 80,
                    "y": 345.13396321821295
                },
                {
                    "x": 80,
                    "y": 345.13396321821295
                },
                {
                    "x": 80,
                    "y": 345.13396321821295
                },
                {
                    "x": 80,
                    "y": 345.13396321821295
                },
                {
                    "x": 80,
                    "y": 345.13396321821295
                },
                {
                    "x": 80,
                    "y": 345.13396321821295
                },
                {
                    "x": 80,
                    "y": 345.13396321821295
                },
                {
                    "x": 80,
                    "y": 345.13396321821295
                },
                {
                    "x": 80,
                    "y": 345.13396321821295
                },
                {
                    "x": 80,
                    "y": 345.13396321821295
                },
                {
                    "x": 80,
                    "y": 345.13396321821295
                },
                {
                    "x": 80,
                    "y": 345.13396321821295
                },
                {
                    "x": 80,
                    "y": 345.13396321821295
                },
                {
                    "x": 80,
                    "y": 345.13396321821295
                },
                {
                    "x": 80,
                    "y": 345.13396321821295
                },
                {
                    "x": 80,
                    "y": 345.13396321821295
                },
                {
                    "x": 80,
                    "y": 345.13396321821295
                },
                {
                    "x": 80,
                    "y": 345.13396321821295
                },
                {
                    "x": 80,
                    "y": 345.13396321821295
                },
                {
                    "x": 80,
                    "y": 345.13396321821295
                },
                {
                    "x": 80,
                    "y": 345.13396321821295
                },
                {
                    "x": 80,
                    "y": 345.13396321821295
                },
                {
                    "x": 80,
                    "y": 345.13396321821295
                },
                {
                    "x": 80,
                    "y": 345.13396321821295
                },
                {
                    "x": 80,
                    "y": 345.13396321821295
                },
                {
                    "x": 80,
                    "y": 345.13396321821295
                },
                {
                    "x": 80,
                    "y": 345.13396321821295
                },
                {
                    "x": 80,
                    "y": 345.13396321821295
                },
                {
                    "x": 80,
                    "y": 345.13396321821295
                },
                {
                    "x": 80,
                    "y": 345.13396321821295
                },
                {
                    "x": 80,
                    "y": 345.13396321821295
                },
                {
                    "x": 80,
                    "y": 345.13396321821295
                },
                {
                    "x": 80,
                    "y": 345.13396321821295
                },
                {
                    "x": 80,
                    "y": 345.13396321821295
                },
                {
                    "x": 80,
                    "y": 345.13396321821295
                },
                {
                    "x": 80,
                    "y": 345.13396321821295
                },
                {
                    "x": 80,
                    "y": 345.13396321821295
                },
                {
                    "x": 80,
                    "y": 345.13396321821295
                },
                {
                    "x": 80,
                    "y": 345.13396321821295
                },
                {
                    "x": 80,
                    "y": 345.13396321821295
                },
                {
                    "x": 80,
                    "y": 345.13396321821295
                },
                {
                    "x": 80,
                    "y": 345.13396321821295
                },
                {
                    "x": 80,
                    "y": 345.13396321821295
                },
                {
                    "x": 80,
                    "y": 345.13396321821295
                },
                {
                    "x": 80,
                    "y": 345.13396321821295
                },
                {
                    "x": 80,
                    "y": 345.13396321821295
                },
                {
                    "x": 80,
                    "y": 345.13396321821295
                },
                {
                    "x": 80,
                    "y": 345.13396321821295
                },
                {
                    "x": 80,
                    "y": 345.13396321821295
                },
                {
                    "x": 80,
                    "y": 345.13396321821295
                },
                {
                    "x": 80,
                    "y": 345.13396321821295
                },
                {
                    "x": 80,
                    "y": 345.13396321821295
                },
                {
                    "x": 80,
                    "y": 345.13396321821295
                },
                {
                    "x": 80,
                    "y": 345.13396321821295
                },
                {
                    "x": 80,
                    "y": 345.13396321821295
                },
                {
                    "x": 80,
                    "y": 345.13396321821295
                },
                {
                    "x": 80,
                    "y": 345.13396321821295
                },
                {
                    "x": 80,
                    "y": 345.13396321821295
                },
                {
                    "x": 80,
                    "y": 345.13396321821295
                },
                {
                    "x": 80,
                    "y": 345.13396321821295
                },
                {
                    "x": 80,
                    "y": 345.13396321821295
                },
                {
                    "x": 80,
                    "y": 345.13396321821295
                },
                {
                    "x": 80,
                    "y": 345.13396321821295
                },
                {
                    "x": 80,
                    "y": 345.13396321821295
                },
                {
                    "x": 80,
                    "y": 345.13396321821295
                },
                {
                    "x": 80,
                    "y": 345.13396321821295
                },
                {
                    "x": 80,
                    "y": 345.13396321821295
                },
                {
                    "x": 80,
                    "y": 345.13396321821295
                },
                {
                    "x": 80,
                    "y": 345.13396321821295
                },
                {
                    "x": 80,
                    "y": 345.13396321821295
                },
                {
                    "x": 80,
                    "y": 345.13396321821295
                },
                {
                    "x": 80,
                    "y": 345.13396321821295
                },
                {
                    "x": 80,
                    "y": 345.13396321821295
                },
                {
                    "x": 80,
                    "y": 345.13396321821295
                },
                {
                    "x": 80,
                    "y": 345.13396321821295
                },
                {
                    "x": 80,
                    "y": 345.13396321821295
                },
                {
                    "x": 80,
                    "y": 345.13396321821295
                },
                {
                    "x": 80,
                    "y": 345.13396321821295
                },
                {
                    "x": 80,
                    "y": 345.13396321821295
                },
                {
                    "x": 80,
                    "y": 345.13396321821295
                },
                {
                    "x": 80,
                    "y": 345.13396321821295
                },
                {
                    "x": 80,
                    "y": 345.13396321821295
                },
                {
                    "x": 80,
                    "y": 345.13396321821295
                },
                {
                    "x": 80,
                    "y": 345.13396321821295
                },
                {
                    "x": 80,
                    "y": 345.13396321821295
                },
                {
                    "x": 80,
                    "y": 345.13396321821295
                },
                {
                    "x": 80,
                    "y": 345.13396321821295
                },
                {
                    "x": 80,
                    "y": 345.13396321821295
                },
                {
                    "x": 80,
                    "y": 345.13396321821295
                },
                {
                    "x": 80,
                    "y": 345.13396321821295
                },
                {
                    "x": 80,
                    "y": 345.13396321821295
                },
                {
                    "x": 80,
                    "y": 345.13396321821295
                },
                {
                    "x": 80,
                    "y": 345.13396321821295
                },
                {
                    "x": 80,
                    "y": 345.13396321821295
                },
                {
                    "x": 80,
                    "y": 345.13396321821295
                },
                {
                    "x": 80,
                    "y": 345.13396321821295
                },
                {
                    "x": 80,
                    "y": 345.13396321821295
                },
                {
                    "x": 80,
                    "y": 345.13396321821295
                },
                {
                    "x": 80,
                    "y": 345.13396321821295
                },
                {
                    "x": 80,
                    "y": 345.13396321821295
                },
                {
                    "x": 80,
                    "y": 345.13396321821295
                },
                {
                    "x": 80,
                    "y": 345.13396321821295
                },
                {
                    "x": 80,
                    "y": 345.13396321821295
                },
                {
                    "x": 80,
                    "y": 345.13396321821295
                },
                {
                    "x": 80,
                    "y": 345.13396321821295
                },
                {
                    "x": 80,
                    "y": 345.13396321821295
                },
                {
                    "x": 80,
                    "y": 345.13396321821295
                },
                {
                    "x": 80,
                    "y": 345.13396321821295
                },
                {
                    "x": 80,
                    "y": 345.13396321821295
                },
                {
                    "x": 80,
                    "y": 345.13396321821295
                },
                {
                    "x": 80,
                    "y": 345.13396321821295
                },
                {
                    "x": 80,
                    "y": 345.13396321821295
                },
                {
                    "x": 80,
                    "y": 345.13396321821295
                },
                {
                    "x": 80,
                    "y": 345.13396321821295
                },
                {
                    "x": 80,
                    "y": 345.13396321821295
                },
                {
                    "x": 80,
                    "y": 345.13396321821295
                },
                {
                    "x": 80,
                    "y": 345.13396321821295
                },
                {
                    "x": 80,
                    "y": 345.13396321821295
                },
                {
                    "x": 80,
                    "y": 345.13396321821295
                },
                {
                    "x": 80,
                    "y": 345.13396321821295
                },
                {
                    "x": 80,
                    "y": 345.13396321821295
                },
                {
                    "x": 80,
                    "y": 345.13396321821295
                },
                {
                    "x": 80,
                    "y": 345.13396321821295
                },
                {
                    "x": 80,
                    "y": 345.13396321821295
                },
                {
                    "x": 80,
                    "y": 345.13396321821295
                },
                {
                    "x": 80,
                    "y": 345.13396321821295
                },
                {
                    "x": 80,
                    "y": 345.13396321821295
                },
                {
                    "x": 80,
                    "y": 345.13396321821295
                },
                {
                    "x": 80,
                    "y": 345.13396321821295
                },
                {
                    "x": 80,
                    "y": 345.13396321821295
                },
                {
                    "x": 80,
                    "y": 345.13396321821295
                },
                {
                    "x": 80,
                    "y": 345.13396321821295
                },
                {
                    "x": 80,
                    "y": 345.13396321821295
                },
                {
                    "x": 80,
                    "y": 345.13396321821295
                },
                {
                    "x": 80,
                    "y": 345.13396321821295
                },
                {
                    "x": 80,
                    "y": 345.13396321821295
                },
                {
                    "x": 80,
                    "y": 345.13396321821295
                },
                {
                    "x": 80,
                    "y": 345.13396321821295
                },
                {
                    "x": 80,
                    "y": 345.13396321821295
                },
                {
                    "x": 80,
                    "y": 345.13396321821295
                },
                {
                    "x": 80,
                    "y": 345.13396321821295
                },
                {
                    "x": 80,
                    "y": 345.13396321821295
                },
                {
                    "x": 80,
                    "y": 345.13396321821295
                },
                {
                    "x": 80,
                    "y": 345.13396321821295
                },
                {
                    "x": 80,
                    "y": 345.13396321821295
                },
                {
                    "x": 80,
                    "y": 345.13396321821295
                },
                {
                    "x": 80,
                    "y": 345.13396321821295
                },
                {
                    "x": 80,
                    "y": 345.13396321821295
                },
                {
                    "x": 80,
                    "y": 345.13396321821295
                },
                {
                    "x": 80,
                    "y": 345.13396321821295
                },
                {
                    "x": 80,
                    "y": 345.13396321821295
                },
                {
                    "x": 80,
                    "y": 345.13396321821295
                },
                {
                    "x": 80,
                    "y": 345.13396321821295
                },
                {
                    "x": 80,
                    "y": 345.13396321821295
                },
                {
                    "x": 80,
                    "y": 345.13396321821295
                },
                {
                    "x": 80,
                    "y": 345.13396321821295
                },
                {
                    "x": 80,
                    "y": 345.13396321821295
                },
                {
                    "x": 80,
                    "y": 345.13396321821295
                },
                {
                    "x": 80,
                    "y": 345.13396321821295
                },
                {
                    "x": 80,
                    "y": 345.13396321821295
                },
                {
                    "x": 80,
                    "y": 345.13396321821295
                },
                {
                    "x": 80,
                    "y": 345.13396321821295
                },
                {
                    "x": 80,
                    "y": 345.13396321821295
                },
                {
                    "x": 80,
                    "y": 345.13396321821295
                },
                {
                    "x": 80,
                    "y": 345.13396321821295
                },
                {
                    "x": 80,
                    "y": 345.13396321821295
                },
                {
                    "x": 80,
                    "y": 345.13396321821295
                },
                {
                    "x": 80,
                    "y": 345.13396321821295
                },
                {
                    "x": 80,
                    "y": 345.13396321821295
                },
                {
                    "x": 80,
                    "y": 345.13396321821295
                },
                {
                    "x": 80,
                    "y": 345.13396321821295
                },
                {
                    "x": 80,
                    "y": 345.13396321821295
                },
                {
                    "x": 80,
                    "y": 345.13396321821295
                },
                {
                    "x": 80,
                    "y": 345.13396321821295
                },
                {
                    "x": 80,
                    "y": 345.13396321821295
                },
                {
                    "x": 80,
                    "y": 345.13396321821295
                },
                {
                    "x": 80,
                    "y": 345.13396321821295
                },
                {
                    "x": 80,
                    "y": 345.13396321821295
                },
                {
                    "x": 80,
                    "y": 345.13396321821295
                },
                {
                    "x": 80,
                    "y": 345.13396321821295
                },
                {
                    "x": 80,
                    "y": 345.13396321821295
                },
                {
                    "x": 80,
                    "y": 345.13396321821295
                },
                {
                    "x": 80,
                    "y": 345.13396321821295
                },
                {
                    "x": 80,
                    "y": 345.13396321821295
                },
                {
                    "x": 80,
                    "y": 345.13396321821295
                },
                {
                    "x": 80,
                    "y": 345.13396321821295
                },
                {
                    "x": 80,
                    "y": 345.13396321821295
                },
                {
                    "x": 80,
                    "y": 345.13396321821295
                },
                {
                    "x": 80,
                    "y": 345.13396321821295
                },
                {
                    "x": 80,
                    "y": 345.13396321821295
                },
                {
                    "x": 80,
                    "y": 345.13396321821295
                },
                {
                    "x": 80,
                    "y": 345.13396321821295
                },
                {
                    "x": 80,
                    "y": 345.13396321821295
                },
                {
                    "x": 80,
                    "y": 345.13396321821295
                },
                {
                    "x": 80,
                    "y": 345.13396321821295
                },
                {
                    "x": 80,
                    "y": 345.13396321821295
                },
                {
                    "x": 80,
                    "y": 345.13396321821295
                },
                {
                    "x": 80,
                    "y": 345.13396321821295
                },
                {
                    "x": 80,
                    "y": 345.13396321821295
                },
                {
                    "x": 80,
                    "y": 345.13396321821295
                },
                {
                    "x": 80,
                    "y": 345.13396321821295
                },
                {
                    "x": 80,
                    "y": 345.13396321821295
                },
                {
                    "x": 80,
                    "y": 345.13396321821295
                },
                {
                    "x": 80,
                    "y": 345.13396321821295
                },
                {
                    "x": 80,
                    "y": 345.13396321821295
                },
                {
                    "x": 80,
                    "y": 345.13396321821295
                },
                {
                    "x": 80,
                    "y": 345.13396321821295
                },
                {
                    "x": 80,
                    "y": 345.13396321821295
                },
                {
                    "x": 80,
                    "y": 345.13396321821295
                },
                {
                    "x": 80,
                    "y": 345.13396321821295
                },
                {
                    "x": 80,
                    "y": 345.13396321821295
                },
                {
                    "x": 80,
                    "y": 345.13396321821295
                },
                {
                    "x": 80,
                    "y": 345.13396321821295
                },
                {
                    "x": 80,
                    "y": 345.13396321821295
                },
                {
                    "x": 80,
                    "y": 345.13396321821295
                },
                {
                    "x": 80,
                    "y": 345.13396321821295
                },
                {
                    "x": 80,
                    "y": 345.13396321821295
                },
                {
                    "x": 80,
                    "y": 345.13396321821295
                },
                {
                    "x": 80,
                    "y": 345.13396321821295
                },
                {
                    "x": 80,
                    "y": 345.13396321821295
                },
                {
                    "x": 80,
                    "y": 345.13396321821295
                },
                {
                    "x": 80,
                    "y": 345.13396321821295
                },
                {
                    "x": 80,
                    "y": 345.13396321821295
                },
                {
                    "x": 80,
                    "y": 345.13396321821295
                },
                {
                    "x": 80,
                    "y": 345.13396321821295
                },
                {
                    "x": 80,
                    "y": 345.13396321821295
                },
                {
                    "x": 80,
                    "y": 345.13396321821295
                },
                {
                    "x": 80,
                    "y": 345.13396321821295
                },
                {
                    "x": 80,
                    "y": 345.13396321821295
                },
                {
                    "x": 80,
                    "y": 345.13396321821295
                },
                {
                    "x": 80,
                    "y": 345.13396321821295
                },
                {
                    "x": 80,
                    "y": 345.13396321821295
                },
                {
                    "x": 80,
                    "y": 345.13396321821295
                },
                {
                    "x": 80,
                    "y": 345.13396321821295
                },
                {
                    "x": 80,
                    "y": 345.13396321821295
                },
                {
                    "x": 80,
                    "y": 345.13396321821295
                },
                {
                    "x": 80,
                    "y": 345.13396321821295
                },
                {
                    "x": 80,
                    "y": 345.13396321821295
                },
                {
                    "x": 80,
                    "y": 345.13396321821295
                },
                {
                    "x": 80,
                    "y": 345.13396321821295
                },
                {
                    "x": 80,
                    "y": 345.13396321821295
                },
                {
                    "x": 80,
                    "y": 345.13396321821295
                },
                {
                    "x": 80,
                    "y": 345.13396321821295
                },
                {
                    "x": 80,
                    "y": 345.13396321821295
                },
                {
                    "x": 80,
                    "y": 345.13396321821295
                },
                {
                    "x": 80,
                    "y": 345.13396321821295
                },
                {
                    "x": 80,
                    "y": 345.13396321821295
                },
                {
                    "x": 80,
                    "y": 345.13396321821295
                },
                {
                    "x": 80,
                    "y": 345.13396321821295
                },
                {
                    "x": 80,
                    "y": 345.13396321821295
                },
                {
                    "x": 80,
                    "y": 345.13396321821295
                },
                {
                    "x": 80,
                    "y": 345.13396321821295
                },
                {
                    "x": 80,
                    "y": 345.13396321821295
                },
                {
                    "x": 80,
                    "y": 345.13396321821295
                },
                {
                    "x": 80,
                    "y": 345.13396321821295
                },
                {
                    "x": 80,
                    "y": 345.13396321821295
                },
                {
                    "x": 80,
                    "y": 345.13396321821295
                },
                {
                    "x": 80,
                    "y": 345.13396321821295
                },
                {
                    "x": 80,
                    "y": 345.13396321821295
                },
                {
                    "x": 80,
                    "y": 345.13396321821295
                },
                {
                    "x": 80,
                    "y": 345.13396321821295
                },
                {
                    "x": 80,
                    "y": 345.13396321821295
                },
                {
                    "x": 80,
                    "y": 345.13396321821295
                },
                {
                    "x": 80,
                    "y": 345.13396321821295
                },
                {
                    "x": 80,
                    "y": 345.13396321821295
                },
                {
                    "x": 80,
                    "y": 345.13396321821295
                },
                {
                    "x": 80,
                    "y": 345.13396321821295
                },
                {
                    "x": 80,
                    "y": 345.13396321821295
                },
                {
                    "x": 80,
                    "y": 345.13396321821295
                },
                {
                    "x": 80,
                    "y": 345.13396321821295
                },
                {
                    "x": 80,
                    "y": 345.13396321821295
                },
                {
                    "x": 80,
                    "y": 345.13396321821295
                },
                {
                    "x": 80,
                    "y": 345.13396321821295
                },
                {
                    "x": 80,
                    "y": 345.13396321821295
                },
                {
                    "x": 80,
                    "y": 345.13396321821295
                },
                {
                    "x": 80,
                    "y": 345.13396321821295
                },
                {
                    "x": 80,
                    "y": 345.13396321821295
                },
                {
                    "x": 80,
                    "y": 345.13396321821295
                },
                {
                    "x": 80,
                    "y": 345.13396321821295
                },
                {
                    "x": 80,
                    "y": 345.13396321821295
                },
                {
                    "x": 80,
                    "y": 345.13396321821295
                },
                {
                    "x": 80,
                    "y": 345.13396321821295
                },
                {
                    "x": 80,
                    "y": 345.13396321821295
                },
                {
                    "x": 80,
                    "y": 345.13396321821295
                },
                {
                    "x": 80,
                    "y": 345.13396321821295
                },
                {
                    "x": 80,
                    "y": 345.13396321821295
                },
                {
                    "x": 80,
                    "y": 345.13396321821295
                },
                {
                    "x": 80,
                    "y": 345.13396321821295
                },
                {
                    "x": 80,
                    "y": 345.13396321821295
                },
                {
                    "x": 80,
                    "y": 345.13396321821295
                },
                {
                    "x": 80,
                    "y": 345.13396321821295
                },
                {
                    "x": 80,
                    "y": 345.13396321821295
                },
                {
                    "x": 80,
                    "y": 345.13396321821295
                },
                {
                    "x": 80,
                    "y": 345.13396321821295
                },
                {
                    "x": 80,
                    "y": 345.13396321821295
                },
                {
                    "x": 80,
                    "y": 345.13396321821295
                },
                {
                    "x": 80,
                    "y": 345.13396321821295
                },
                {
                    "x": 80,
                    "y": 345.13396321821295
                },
                {
                    "x": 80,
                    "y": 345.13396321821295
                },
                {
                    "x": 80,
                    "y": 345.13396321821295
                },
                {
                    "x": 80,
                    "y": 345.13396321821295
                },
                {
                    "x": 80,
                    "y": 345.13396321821295
                },
                {
                    "x": 80,
                    "y": 345.13396321821295
                },
                {
                    "x": 80,
                    "y": 345.13396321821295
                },
                {
                    "x": 80,
                    "y": 345.13396321821295
                },
                {
                    "x": 80,
                    "y": 345.13396321821295
                },
                {
                    "x": 80,
                    "y": 345.13396321821295
                },
                {
                    "x": 80,
                    "y": 345.13396321821295
                },
                {
                    "x": 80,
                    "y": 345.13396321821295
                },
                {
                    "x": 80,
                    "y": 345.13396321821295
                },
                {
                    "x": 80,
                    "y": 345.13396321821295
                },
                {
                    "x": 80,
                    "y": 345.13396321821295
                },
                {
                    "x": 80,
                    "y": 345.13396321821295
                }
            ],
            "marbleEndDist": 0,
            "marbleMinDist": 0,
            "runOutcome": "goal",
            "drawnLines": [],
            "drawnPhysObj": [],
            "trialStartTime": 1703865020080,
            "drawTime": 11674,
            "runTime": 5362
        }
    ],
    "tutorialsurvey": [],
    "endsurvey": null,
    "demographic": null,
    "bonus": ""
}